README.rst
setup.cfg
setup.py
hcm/__init__.py
hcm/__main__.py
hcm/utils.py
hcm/version.py
hcm.egg-info/PKG-INFO
hcm.egg-info/SOURCES.txt
hcm.egg-info/dependency_links.txt
hcm.egg-info/entry_points.txt
hcm.egg-info/not-zip-safe
hcm.egg-info/requires.txt
hcm.egg-info/top_level.txt
hcm/subcommand/__init__.py
hcm/subcommand/browse.py
hcm/subcommand/create.py
hcm/subcommand/download.py
hcm/subcommand/install.py
hcm/subcommand/publish.py
hcm/subcommand/show.py
hcm/subcommand/sub_list.py
hcm/subcommand/uninstall.py
hcm/subcommand/validate.py
hcm/svn/__init__.py
hcm/svn/extract_hcm_json_revision.py
hcm/svn/svn.py
hcm/svn/what_is_the_latest_file_revision.py
tests/__init__.py
tests/mocks.py
tests/subcommand/__init__.py
tests/subcommand/browse/__init__.py
tests/subcommand/browse/test_browse.py
tests/subcommand/create/__init__.py
tests/subcommand/create/test_create.py
tests/subcommand/download/__init__.py
tests/subcommand/download/test_download.py
tests/subcommand/install/__init__.py
tests/subcommand/install/test_install.py
tests/subcommand/publish/__init__.py
tests/subcommand/publish/test_publish.py
tests/subcommand/show/__init__.py
tests/subcommand/show/test_show.py
tests/subcommand/sub_list/__init__.py
tests/subcommand/sub_list/test_sub_list.py
tests/subcommand/validate/__init__.py
tests/subcommand/validate/test_validate.py
tests/svn/__init__.py
tests/svn/test_svn.py
tests/utils/__init__.py
tests/utils/test_utils.py
tests/version/__init__.py
tests/version/test_version.py