Metadata-Version: 1.1
Name: hcm
Version: 0.14
Summary: HDL Component Manager
Home-page: https://github.com/jeremiah-c-leary/hdl-component-manager
Author: Jeremiah C Leary
Author-email: jeremiah.c.leary@gmail.com
License: GNU General Public License
Download-URL: https://github.com/jeremiah-c-leary/hdl-component-manager
Keywords: vhdl,verilog,packager,configuration management
Platform: UNKNOWN
Classifier: Development Status :: 4 - Beta
Classifier: Environment :: Console
Classifier: Programming Language :: Python :: 3
Classifier: Intended Audience :: End Users/Desktop
Classifier: License :: OSI Approved :: GNU General Public License v3 (GPLv3)
Classifier: Natural Language :: English
Classifier: Operating System :: POSIX :: Linux
Classifier: Topic :: System :: Archiving :: Packaging
